hyperdb/__init__.py
hyperdb/gcp.py
hyperdb/local_files.py
hyperdb/ms_azure.py
hyperdb/tableau_server.py
hyperdb-0.1.1.dist-info/LICENSE
hyperdb-0.1.1.dist-info/METADATA
hyperdb-0.1.1.dist-info/WHEEL
hyperdb-0.1.1.dist-info/top_level.txt
hyperdb-0.1.1.dist-info/RECORD
