Metadata-Version: 2.1
Name: hyperdb
Version: 0.1.1
Summary: Hyperdb provides wrapper functions for working with Tableau hyper datasources and moving data between Tableau Server, Google Cloud Platform and Microsoft Azure through a common interface
Home-page: http://github.com/mhadi813/hyperdb
Author: Muhammad Hadi
Author-email: mhadi813@gmail.com
License: BSD
Keywords: tableau hyper pandas google bigquery cloud storage azure sql database
Platform: UNKNOWN
Classifier: Development Status :: 4 - Beta
Classifier: Intended Audience :: Developers
Classifier: Topic :: Office/Business
Classifier: License :: OSI Approved :: BSD License
Classifier: Programming Language :: Python :: 3.6
Classifier: Programming Language :: Python :: 3.7
Classifier: Programming Language :: Python :: 3.8
Requires-Dist: pandas (==1.0.3)
Requires-Dist: google-cloud-bigquery (==1.24.0)
Requires-Dist: google-cloud-storage (==1.24.1)
Requires-Dist: gcsfs (==0.6.0)
Requires-Dist: azure-storage-blob (==1.5.0)
Requires-Dist: pyarrow (==0.16.0)
Requires-Dist: requests (==2.23.0)
Requires-Dist: requests-ntlm (==1.1.0)
Requires-Dist: xlrd (==1.2.0)
Requires-Dist: pyodbc (==4.0.27)
Requires-Dist: sqlalchemy
Requires-Dist: tableauhyperapi (==0.0.10622)
Requires-Dist: tableauserverclient (==0.10)
Requires-Dist: pantab (==1.1.0)
